odoo8_addon_framework_agreement_sourcing_stock_route_transit-8.0.0.1.0-py2.7-nspkg.pth
odoo_addons/framework_agreement_sourcing_stock_route_transit/__openerp__.py
odoo_addons/framework_agreement_sourcing_stock_route_transit/__init__.py
odoo_addons/framework_agreement_sourcing_stock_route_transit/README.rst
odoo_addons/framework_agreement_sourcing_stock_route_transit/model/logistic_requisition_source.py
odoo_addons/framework_agreement_sourcing_stock_route_transit/model/__init__.py
odoo_addons/framework_agreement_sourcing_stock_route_transit/tests/test_agreement_source_line_to_po.py
odoo_addons/framework_agreement_sourcing_stock_route_transit/tests/__init__.py
odoo8_addon_framework_agreement_sourcing_stock_route_transit-8.0.0.1.0.dist-info/top_level.txt
odoo8_addon_framework_agreement_sourcing_stock_route_transit-8.0.0.1.0.dist-info/WHEEL
odoo8_addon_framework_agreement_sourcing_stock_route_transit-8.0.0.1.0.dist-info/RECORD
odoo8_addon_framework_agreement_sourcing_stock_route_transit-8.0.0.1.0.dist-info/metadata.json
odoo8_addon_framework_agreement_sourcing_stock_route_transit-8.0.0.1.0.dist-info/DESCRIPTION.rst
odoo8_addon_framework_agreement_sourcing_stock_route_transit-8.0.0.1.0.dist-info/METADATA
odoo8_addon_framework_agreement_sourcing_stock_route_transit-8.0.0.1.0.dist-info/namespace_packages.txt
